alea_markdown/__init__.py
alea_markdown/auto_parser.py
alea_markdown/cli.py
alea_markdown/logger.py
alea_markdown/lxml_parser.py
alea_markdown/markdownify_parser.py
alea_markdown/normalizer.py
alea_markdown/regex_parser.py
alea_markdown/base/__init__.py
alea_markdown/base/html_types.py
alea_markdown/base/markdown_types.py
alea_markdown/base/parser.py
alea_markdown/base/parser_config.py
alea_markdown-0.1.1.dist-info/METADATA
alea_markdown-0.1.1.dist-info/WHEEL
alea_markdown-0.1.1.dist-info/entry_points.txt
alea_markdown-0.1.1.dist-info/licenses/LICENSE
alea_markdown-0.1.1.dist-info/RECORD
