Metadata-Version: 2.4
Name: alea-markdown
Version: 0.1.1
Summary: Convert HTML files to Markdown with configurable options (pure Python)
Project-URL: Homepage, https://github.com/alea-institute/alea-markdown-python
Project-URL: Bug Tracker, https://github.com/alea-institute/alea-markdown-python/issues
Project-URL: Documentation, https://github.com/alea-institute/alea-markdown-python#readme
Project-URL: Source, https://github.com/alea-institute/alea-markdown-python
Author: ALEA Institute
License-File: LICENSE
Classifier: License :: OSI Approved :: MIT License
Classifier: Operating System :: OS Independent
Classifier: Programming Language :: Python :: 3
Classifier: Topic :: Text Processing :: Markup :: HTML
Classifier: Topic :: Text Processing :: Markup :: Markdown
Requires-Python: >=3.12
Requires-Dist: lxml>=5.3.1
Provides-Extra: markdownify
Requires-Dist: markdownify>=0.11.6; extra == 'markdownify'
